[{"new_object_id": "sofa_1", "style": "minimalist", "material": "fabric", "functionality": "seating", "color": "white", "size_in_meters": {"length": 3.0, "width": 1.0, "height": 0.8}, "is_on_the_floor": true, "facing": "north_wall", "placement": {"room_layout_elements": [{"layout_element_id": "south_wall", "preposition": "on"}], "objects_in_room": []}, "cluster": {"constraint_area": {"x_neg": 0.0, "x_pos": 0.0, "y_neg": 0.0, "y_pos": 0.0}}, "rotation": {"z_angle": 0.0}, "position": {"x": 2.228054571581781, "y": 0.5, "z": 0.4}}]